codebase_digest/__init__.py
codebase_digest/app.py
codebase_digest-0.1.43.dist-info/METADATA
codebase_digest-0.1.43.dist-info/WHEEL
codebase_digest-0.1.43.dist-info/entry_points.txt
codebase_digest-0.1.43.dist-info/top_level.txt
codebase_digest-0.1.43.dist-info/RECORD
