Metadata-Version: 2.1
Name: codebase-digest
Version: 0.1.43
Summary: Consolidates and analyzes codebases for insights.
Home-page: https://github.com/kamilstanuch/codebase-digest
Author: Kamil Stanuch
Keywords: code analysis,codebase,consolidation,visualization
Classifier: Development Status :: 3 - Alpha
Classifier: Intended Audience :: Developers
Classifier: Topic :: Software Development :: Libraries :: Python Modules
Classifier: Programming Language :: Python :: 3
Classifier: License :: OSI Approved :: MIT License
Classifier: Operating System :: OS Independent
Requires-Python: >=3.6
Requires-Dist: certifi >=2024.8.30
Requires-Dist: cffi >=1.17.1
Requires-Dist: charset-normalizer >=3.3.2
Requires-Dist: colorama >=0.4.6
Requires-Dist: cryptography >=43.0.1
Requires-Dist: Deprecated >=1.2.14
Requires-Dist: idna >=3.10
Requires-Dist: pycparser >=2.22
Requires-Dist: PyGithub >=2.4.0
Requires-Dist: PyJWT >=2.9.0
Requires-Dist: PyNaCl >=1.5.0
Requires-Dist: pyperclip >=1.9.0
Requires-Dist: regex >=2024.9.11
Requires-Dist: requests >=2.32.3
Requires-Dist: tiktoken >=0.8.0
Requires-Dist: typing-extensions >=4.12.2
Requires-Dist: urllib3 >=2.2.3
Requires-Dist: wrapt >=1.16.0
Requires-Dist: keyring
Provides-Extra: dev
Requires-Dist: PyGithub ; extra == 'dev'
Requires-Dist: twine ; extra == 'dev'
Requires-Dist: packaging ; extra == 'dev'
Requires-Dist: setuptools ; extra == 'dev'
